phase_unwrap/__init__.py
phase_unwrap/_static_version.py
phase_unwrap/_version.py
phase_unwrap/cli.py
phase_unwrap-2.0.0.dist-info/LICENSE
phase_unwrap-2.0.0.dist-info/METADATA
phase_unwrap-2.0.0.dist-info/WHEEL
phase_unwrap-2.0.0.dist-info/entry_points.txt
phase_unwrap-2.0.0.dist-info/top_level.txt
phase_unwrap-2.0.0.dist-info/RECORD
