Metadata-Version: 2.1
Name: phase_unwrap
Version: 2.0.0
Summary: A simple, laplacian-based unwrapping pipeline for MRI phase images in Python.
Home-page: https://github.com/blakedewey/phase_unwrap
Author: Blake Dewey
Author-email: blake.dewey@jhu.edu
License: GPL-3.0
Keywords: mri phase unwrapping
Classifier: Development Status :: 5 - Production/Stable
Classifier: Environment :: Console
Classifier: Intended Audience :: Science/Research
Classifier: Topic :: Scientific/Engineering
Classifier: License :: OSI Approved :: GNU General Public License v3 (GPLv3)
Classifier: Programming Language :: Python :: 3.8
Classifier: Programming Language :: Python :: 3.9
Classifier: Programming Language :: Python :: 3.10
Classifier: Programming Language :: Python :: 3.11
Classifier: Programming Language :: Python :: 3.12
Requires-Python: >=3.8
License-File: LICENSE
Requires-Dist: nibabel
Requires-Dist: numpy
